{"cameraMode":{"drawMode":0,"name":"Shaded","section":"Shading Mode"},"sceneLighting":true,"audioPlay":false,"sceneViewState":{"showFog":true,"showMaterialUpdate":false,"showSkybox":true,"showFlares":true,"showImageEffects":true,"showParticleSystems":true},"in2DMode":false,"pivot":{"x":-5.583304405212402,"y":4.519423484802246,"z":22.373092651367189},"rotation":{"x":0.0004201175179332495,"y":-0.9882693290710449,"z":0.15269754827022553,"w":0.0026628850027918817},"size":1.7428960800170899,"orthographic":false}